LICENSE.md
bitrise_reports/__init__.py
bitrise_reports/app.py
bitrise_reports/bitrise.py
bitrise_reports/cli.py
bitrise_reports/di.py
bitrise_reports/entrypoint.py
bitrise_reports/errors.py
bitrise_reports/metrics.py
bitrise_reports/middleware.py
bitrise_reports/models.py
bitrise_reports/reporting.py
bitrise_reports-0.2.0.dist-info/entry_points.txt
bitrise_reports-0.2.0.dist-info/LICENSE.md
bitrise_reports-0.2.0.dist-info/WHEEL
bitrise_reports-0.2.0.dist-info/METADATA
bitrise_reports-0.2.0.dist-info/RECORD
