Metadata-Version: 2.1
Name: bitrise-reports
Version: 0.2.0
Summary: The missing tool to extract reports about projects you build on Bitrise
Home-page: https://github.com/dotanuki-labs/bitrise-reports
License: MIT
Author: Ubiratan Soares
Author-email: ubiratanfsoares@gmail.com
Requires-Python: >=3.8,<4.0
Classifier: Environment :: Console
Classifier: License :: OSI Approved :: MIT License
Classifier: Operating System :: OS Independent
Classifier: Programming Language :: Python :: 3
Classifier: Programming Language :: Python :: 3.10
Classifier: Programming Language :: Python :: 3.8
Classifier: Programming Language :: Python :: 3.9
Requires-Dist: click (==8.0.1)
Requires-Dist: openpyxl (==3.0.9)
Requires-Dist: pretty-errors (==1.2.24)
Requires-Dist: python-dateutil (==2.8.2)
Requires-Dist: requests (==2.26.0)
Requires-Dist: rich (==10.12.0)
Project-URL: Repository, https://github.com/dotanuki-labs/bitrise-reports
